app/__init__.py
app/api/__init__.py
app/api/auth.py
app/api/lark_client.py
app/config/__init__.py
app/config/settings.py
app/core/__init__.py
app/core/llm_service.py
app/core/mcp_server.py
app/core/message_service.py
app/db/__init__.py
app/db/models.py
app/db/session.py
app/utils/__init__.py
app/utils/lark_utils.py
builder/__init__.py
builder/header.py
builder/params.py
builder/proto.py
extension/__init__.py
extension/weather_api/GEOIP.db
extension/weather_api/api.py
extension/weather_api/db.py
static/__init__.py
static/lark_decrypt.js
static/proto.proto
static/proto_pb2.py
static/resource/back_end.png
static/resource/front_end.png
static/resource/front_end_1.png
static/resource/front_end_2.png
static/resource/functions.png
iflow_mcp_larkagentx-0.1.0.dist-info/METADATA
iflow_mcp_larkagentx-0.1.0.dist-info/WHEEL
iflow_mcp_larkagentx-0.1.0.dist-info/entry_points.txt
iflow_mcp_larkagentx-0.1.0.dist-info/RECORD
