Metadata-Version: 2.4
Name: iflow-mcp_larkagentx
Version: 0.1.0
Summary: Lark Agent X - AI assistant for Lark/Feishu with MCP support
Requires-Python: >=3.10
Requires-Dist: brotli==1.1.0
Requires-Dist: cryptography==44.0.2
Requires-Dist: fastmcp==2.1.2
Requires-Dist: loguru==0.7.3
Requires-Dist: mcp==1.6.0
Requires-Dist: openai==1.74.0
Requires-Dist: protobuf3-to-dict==0.1.5
Requires-Dist: protobuf==5.29.3
Requires-Dist: pyexecjs==1.5.1
Requires-Dist: pymysql==1.1.0
Requires-Dist: python-dotenv==1.1.0
Requires-Dist: requests==2.31.0
Requires-Dist: sqlalchemy==2.0.30
Requires-Dist: websockets==15.0.1
